<?xml version="1.0" ?>
<FlowMonitor>
  <FlowStats>
    <Flow flowId="1" timeFirstTxPacket="+0.0ns" timeFirstRxPacket="+5040184.0ns" timeLastTxPacket="+499968001.0ns" timeLastRxPacket="+498939882.0ns" delaySum="+590610527.0ns" jitterSum="+842684285.0ns" lastDelay="+123881.0ns" txBytes="693848" rxBytes="692252" txPackets="1304" rxPackets="1301" lostPackets="0" timesForwarded="3903">
      <path time="0" port="1" />
      <path time="1" port="10" />
      <path time="2" port="4" />
      <path time="3" port="1" />
      <delayHistogram nBins="6" >
        <bin index="0" start="0" width="0.001" count="875" />
        <bin index="1" start="0.001" width="0.001" count="424" />
        <bin index="5" start="0.005" width="0.001" count="2" />
      </delayHistogram>
      <jitterHistogram nBins="5" >
        <bin index="0" start="0" width="0.001" count="1298" />
        <bin index="1" start="0.001" width="0.001" count="1" />
        <bin index="4" start="0.004" width="0.001" count="1" />
      </jitterHistogram>
      <packetSizeHistogram nBins="30" >
        <bin index="2" start="40" width="20" count="3" />
        <bin index="17" start="340" width="20" count="1" />
        <bin index="21" start="420" width="20" count="422" />
        <bin index="29" start="580" width="20" count="875" />
      </packetSizeHistogram>
      <flowInterruptionsHistogram nBins="0" >
      </flowInterruptionsHistogram>
    </Flow>
    <Flow flowId="2" timeFirstTxPacket="+0.0ns" timeFirstRxPacket="+5040184.0ns" timeLastTxPacket="+499968001.0ns" timeLastRxPacket="+498940826.0ns" delaySum="+590804127.0ns" jitterSum="+841628491.0ns" lastDelay="+124825.0ns" txBytes="693848" rxBytes="692252" txPackets="1304" rxPackets="1301" lostPackets="0" timesForwarded="3903">
      <path time="0" port="1" />
      <path time="1" port="8" />
      <path time="2" port="3" />
      <path time="3" port="2" />
      <delayHistogram nBins="6" >
        <bin index="0" start="0" width="0.001" count="874" />
        <bin index="1" start="0.001" width="0.001" count="425" />
        <bin index="5" start="0.005" width="0.001" count="2" />
      </delayHistogram>
      <jitterHistogram nBins="5" >
        <bin index="0" start="0" width="0.001" count="1297" />
        <bin index="1" start="0.001" width="0.001" count="2" />
        <bin index="4" start="0.004" width="0.001" count="1" />
      </jitterHistogram>
      <packetSizeHistogram nBins="30" >
        <bin index="2" start="40" width="20" count="3" />
        <bin index="12" start="240" width="20" count="1" />
        <bin index="21" start="420" width="20" count="421" />
        <bin index="25" start="500" width="20" count="1" />
        <bin index="29" start="580" width="20" count="875" />
      </packetSizeHistogram>
      <flowInterruptionsHistogram nBins="0" >
      </flowInterruptionsHistogram>
    </Flow>
    <Flow flowId="3" timeFirstTxPacket="+0.0ns" timeFirstRxPacket="+5040230.0ns" timeLastTxPacket="+499968001.0ns" timeLastRxPacket="+498941298.0ns" delaySum="+591184164.0ns" jitterSum="+841227381.0ns" lastDelay="+125297.0ns" txBytes="693848" rxBytes="692252" txPackets="1304" rxPackets="1301" lostPackets="0" timesForwarded="3903">
      <path time="0" port="1" />
      <path time="1" port="8" />
      <path time="2" port="4" />
      <path time="3" port="3" />
      <delayHistogram nBins="6" >
        <bin index="0" start="0" width="0.001" count="874" />
        <bin index="1" start="0.001" width="0.001" count="425" />
        <bin index="5" start="0.005" width="0.001" count="2" />
      </delayHistogram>
      <jitterHistogram nBins="5" >
        <bin index="0" start="0" width="0.001" count="1297" />
        <bin index="1" start="0.001" width="0.001" count="2" />
        <bin index="4" start="0.004" width="0.001" count="1" />
      </jitterHistogram>
      <packetSizeHistogram nBins="30" >
        <bin index="2" start="40" width="20" count="3" />
        <bin index="12" start="240" width="20" count="1" />
        <bin index="21" start="420" width="20" count="421" />
        <bin index="25" start="500" width="20" count="1" />
        <bin index="29" start="580" width="20" count="875" />
      </packetSizeHistogram>
      <flowInterruptionsHistogram nBins="0" >
      </flowInterruptionsHistogram>
    </Flow>
    <Flow flowId="4" timeFirstTxPacket="+0.0ns" timeFirstRxPacket="+5040230.0ns" timeLastTxPacket="+499968001.0ns" timeLastRxPacket="+498940354.0ns" delaySum="+591574573.0ns" jitterSum="+840976555.0ns" lastDelay="+124353.0ns" txBytes="693848" rxBytes="692252" txPackets="1304" rxPackets="1301" lostPackets="4" timesForwarded="3903">
      <packetsDropped reasonCode="0" number="0" />
      <packetsDropped reasonCode="1" number="0" />
      <packetsDropped reasonCode="2" number="0" />
      <packetsDropped reasonCode="3" number="4" />
      <bytesDropped reasonCode="0" bytes="0" />
      <bytesDropped reasonCode="1" bytes="0" />
      <bytesDropped reasonCode="2" bytes="0" />
      <bytesDropped reasonCode="3" bytes="2352" />
      <path time="0" port="1" />
      <path time="1" port="7" />
      <path time="2" port="3" />
      <path time="3" port="4" />
      <delayHistogram nBins="6" >
        <bin index="0" start="0" width="0.001" count="873" />
        <bin index="1" start="0.001" width="0.001" count="426" />
        <bin index="5" start="0.005" width="0.001" count="2" />
      </delayHistogram>
      <jitterHistogram nBins="5" >
        <bin index="0" start="0" width="0.001" count="1296" />
        <bin index="1" start="0.001" width="0.001" count="3" />
        <bin index="4" start="0.004" width="0.001" count="1" />
      </jitterHistogram>
      <packetSizeHistogram nBins="30" >
        <bin index="2" start="40" width="20" count="3" />
        <bin index="12" start="240" width="20" count="1" />
        <bin index="17" start="340" width="20" count="1" />
        <bin index="21" start="420" width="20" count="420" />
        <bin index="29" start="580" width="20" count="876" />
      </packetSizeHistogram>
      <flowInterruptionsHistogram nBins="0" >
      </flowInterruptionsHistogram>
    </Flow>
    <Flow flowId="5" timeFirstTxPacket="+0.0ns" timeFirstRxPacket="+5040276.0ns" timeLastTxPacket="+499968001.0ns" timeLastRxPacket="+498941770.0ns" delaySum="+592775355.0ns" jitterSum="+839785201.0ns" lastDelay="+125769.0ns" txBytes="693848" rxBytes="692252" txPackets="1304" rxPackets="1301" lostPackets="3" timesForwarded="3903">
      <packetsDropped reasonCode="0" number="0" />
      <packetsDropped reasonCode="1" number="0" />
      <packetsDropped reasonCode="2" number="0" />
      <packetsDropped reasonCode="3" number="3" />
      <bytesDropped reasonCode="0" bytes="0" />
      <bytesDropped reasonCode="1" bytes="0" />
      <bytesDropped reasonCode="2" bytes="0" />
      <bytesDropped reasonCode="3" bytes="1764" />
      <path time="0" port="1" />
      <path time="1" port="8" />
      <path time="2" port="3" />
      <path time="3" port="5" />
      <delayHistogram nBins="6" >
        <bin index="0" start="0" width="0.001" count="873" />
        <bin index="1" start="0.001" width="0.001" count="426" />
        <bin index="5" start="0.005" width="0.001" count="2" />
      </delayHistogram>
      <jitterHistogram nBins="5" >
        <bin index="0" start="0" width="0.001" count="1296" />
        <bin index="1" start="0.001" width="0.001" count="3" />
        <bin index="4" start="0.004" width="0.001" count="1" />
      </jitterHistogram>
      <packetSizeHistogram nBins="30" >
        <bin index="2" start="40" width="20" count="3" />
        <bin index="12" start="240" width="20" count="1" />
        <bin index="17" start="340" width="20" count="1" />
        <bin index="21" start="420" width="20" count="420" />
        <bin index="29" start="580" width="20" count="876" />
      </packetSizeHistogram>
      <flowInterruptionsHistogram nBins="0" >
      </flowInterruptionsHistogram>
    </Flow>
    <Flow flowId="6" timeFirstTxPacket="+0.0ns" timeFirstRxPacket="+5040184.0ns" timeLastTxPacket="+499968001.0ns" timeLastRxPacket="+498939882.0ns" delaySum="+590610355.0ns" jitterSum="+842684027.0ns" lastDelay="+123881.0ns" txBytes="693848" rxBytes="692252" txPackets="1304" rxPackets="1301" lostPackets="0" timesForwarded="3903">
      <path time="0" port="1" />
      <path time="1" port="9" />
      <path time="2" port="3" />
      <path time="3" port="6" />
      <delayHistogram nBins="6" >
        <bin index="0" start="0" width="0.001" count="875" />
        <bin index="1" start="0.001" width="0.001" count="424" />
        <bin index="5" start="0.005" width="0.001" count="2" />
      </delayHistogram>
      <jitterHistogram nBins="5" >
        <bin index="0" start="0" width="0.001" count="1298" />
        <bin index="1" start="0.001" width="0.001" count="1" />
        <bin index="4" start="0.004" width="0.001" count="1" />
      </jitterHistogram>
      <packetSizeHistogram nBins="30" >
        <bin index="2" start="40" width="20" count="3" />
        <bin index="17" start="340" width="20" count="1" />
        <bin index="21" start="420" width="20" count="422" />
        <bin index="29" start="580" width="20" count="875" />
      </packetSizeHistogram>
      <flowInterruptionsHistogram nBins="0" >
      </flowInterruptionsHistogram>
    </Flow>
    <Flow flowId="7" timeFirstTxPacket="+5040184.0ns" timeFirstRxPacket="+10080368.0ns" timeLastTxPacket="+498939882.0ns" timeLastRxPacket="+498979582.0ns" delaySum="+1000785211.0ns" jitterSum="+842785377.0ns" lastDelay="+122233.0ns" txBytes="67664" rxBytes="67560" txPackets="1301" rxPackets="1299" lostPackets="0" timesForwarded="3897">
      <path time="0" port="1" />
      <path time="1" port="7" />
      <path time="2" port="2" />
      <path time="3" port="1" />
      <delayHistogram nBins="6" >
        <bin index="0" start="0" width="0.001" count="452" />
        <bin index="1" start="0.001" width="0.001" count="846" />
        <bin index="5" start="0.005" width="0.001" count="1" />
      </delayHistogram>
      <jitterHistogram nBins="5" >
        <bin index="0" start="0" width="0.001" count="1296" />
        <bin index="1" start="0.001" width="0.001" count="1" />
        <bin index="4" start="0.004" width="0.001" count="1" />
      </jitterHistogram>
      <packetSizeHistogram nBins="3" >
        <bin index="2" start="40" width="20" count="1299" />
      </packetSizeHistogram>
      <flowInterruptionsHistogram nBins="0" >
      </flowInterruptionsHistogram>
    </Flow>
    <Flow flowId="8" timeFirstTxPacket="+5040184.0ns" timeFirstRxPacket="+10080368.0ns" timeLastTxPacket="+498940826.0ns" timeLastRxPacket="+498980998.0ns" delaySum="+552518887.0ns" jitterSum="+909981154.0ns" lastDelay="+41588.0ns" txBytes="67664" rxBytes="67612" txPackets="1301" rxPackets="1300" lostPackets="0" timesForwarded="3900">
      <path time="0" port="1" />
      <path time="1" port="10" />
      <path time="2" port="2" />
      <path time="3" port="2" />
      <delayHistogram nBins="6" >
        <bin index="0" start="0" width="0.001" count="872" />
        <bin index="1" start="0.001" width="0.001" count="427" />
        <bin index="5" start="0.005" width="0.001" count="1" />
      </delayHistogram>
      <jitterHistogram nBins="5" >
        <bin index="0" start="0" width="0.001" count="875" />
        <bin index="1" start="0.001" width="0.001" count="423" />
        <bin index="4" start="0.004" width="0.001" count="1" />
      </jitterHistogram>
      <packetSizeHistogram nBins="3" >
        <bin index="2" start="40" width="20" count="1300" />
      </packetSizeHistogram>
      <flowInterruptionsHistogram nBins="0" >
      </flowInterruptionsHistogram>
    </Flow>
    <Flow flowId="9" timeFirstTxPacket="+5040184.0ns" timeFirstRxPacket="+10080368.0ns" timeLastTxPacket="+498939882.0ns" timeLastRxPacket="+498979582.0ns" delaySum="+1000785340.0ns" jitterSum="+842785205.0ns" lastDelay="+122233.0ns" txBytes="67664" rxBytes="67560" txPackets="1301" rxPackets="1299" lostPackets="0" timesForwarded="3897">
      <path time="0" port="1" />
      <path time="1" port="8" />
      <path time="2" port="1" />
      <path time="3" port="6" />
      <delayHistogram nBins="6" >
        <bin index="0" start="0" width="0.001" count="452" />
        <bin index="1" start="0.001" width="0.001" count="846" />
        <bin index="5" start="0.005" width="0.001" count="1" />
      </delayHistogram>
      <jitterHistogram nBins="5" >
        <bin index="0" start="0" width="0.001" count="1296" />
        <bin index="1" start="0.001" width="0.001" count="1" />
        <bin index="4" start="0.004" width="0.001" count="1" />
      </jitterHistogram>
      <packetSizeHistogram nBins="3" >
        <bin index="2" start="40" width="20" count="1299" />
      </packetSizeHistogram>
      <flowInterruptionsHistogram nBins="0" >
      </flowInterruptionsHistogram>
    </Flow>
    <Flow flowId="10" timeFirstTxPacket="+5040230.0ns" timeFirstRxPacket="+10080414.0ns" timeLastTxPacket="+498941298.0ns" timeLastRxPacket="+498981470.0ns" delaySum="+551713469.0ns" jitterSum="+909550122.0ns" lastDelay="+41588.0ns" txBytes="67664" rxBytes="67612" txPackets="1301" rxPackets="1300" lostPackets="0" timesForwarded="3900">
      <path time="0" port="1" />
      <path time="1" port="10" />
      <path time="2" port="1" />
      <path time="3" port="3" />
      <delayHistogram nBins="6" >
        <bin index="0" start="0" width="0.001" count="872" />
        <bin index="1" start="0.001" width="0.001" count="427" />
        <bin index="5" start="0.005" width="0.001" count="1" />
      </delayHistogram>
      <jitterHistogram nBins="5" >
        <bin index="0" start="0" width="0.001" count="877" />
        <bin index="1" start="0.001" width="0.001" count="421" />
        <bin index="4" start="0.004" width="0.001" count="1" />
      </jitterHistogram>
      <packetSizeHistogram nBins="3" >
        <bin index="2" start="40" width="20" count="1300" />
      </packetSizeHistogram>
      <flowInterruptionsHistogram nBins="0" >
      </flowInterruptionsHistogram>
    </Flow>
    <Flow flowId="11" timeFirstTxPacket="+5040230.0ns" timeFirstRxPacket="+10080414.0ns" timeLastTxPacket="+498940354.0ns" timeLastRxPacket="+498980054.0ns" delaySum="+999904400.0ns" jitterSum="+842865130.0ns" lastDelay="+122368.0ns" txBytes="67664" rxBytes="67560" txPackets="1301" rxPackets="1299" lostPackets="0" timesForwarded="3897">
      <path time="0" port="1" />
      <path time="1" port="8" />
      <path time="2" port="2" />
      <path time="3" port="4" />
      <delayHistogram nBins="6" >
        <bin index="0" start="0" width="0.001" count="452" />
        <bin index="1" start="0.001" width="0.001" count="844" />
        <bin index="2" start="0.002" width="0.001" count="2" />
        <bin index="5" start="0.005" width="0.001" count="1" />
      </delayHistogram>
      <jitterHistogram nBins="5" >
        <bin index="0" start="0" width="0.001" count="1294" />
        <bin index="1" start="0.001" width="0.001" count="2" />
        <bin index="2" start="0.002" width="0.001" count="1" />
        <bin index="4" start="0.004" width="0.001" count="1" />
      </jitterHistogram>
      <packetSizeHistogram nBins="3" >
        <bin index="2" start="40" width="20" count="1299" />
      </packetSizeHistogram>
      <flowInterruptionsHistogram nBins="0" >
      </flowInterruptionsHistogram>
    </Flow>
    <Flow flowId="12" timeFirstTxPacket="+5040276.0ns" timeFirstRxPacket="+10080460.0ns" timeLastTxPacket="+498941770.0ns" timeLastRxPacket="+498981470.0ns" delaySum="+999452793.0ns" jitterSum="+841049987.0ns" lastDelay="+123447.0ns" txBytes="67664" rxBytes="67560" txPackets="1301" rxPackets="1299" lostPackets="0" timesForwarded="3897">
      <path time="0" port="1" />
      <path time="1" port="7" />
      <path time="2" port="2" />
      <path time="3" port="5" />
      <delayHistogram nBins="6" >
        <bin index="0" start="0" width="0.001" count="452" />
        <bin index="1" start="0.001" width="0.001" count="844" />
        <bin index="2" start="0.002" width="0.001" count="2" />
        <bin index="5" start="0.005" width="0.001" count="1" />
      </delayHistogram>
      <jitterHistogram nBins="5" >
        <bin index="0" start="0" width="0.001" count="1294" />
        <bin index="1" start="0.001" width="0.001" count="2" />
        <bin index="2" start="0.002" width="0.001" count="1" />
        <bin index="4" start="0.004" width="0.001" count="1" />
      </jitterHistogram>
      <packetSizeHistogram nBins="3" >
        <bin index="2" start="40" width="20" count="1299" />
      </packetSizeHistogram>
      <flowInterruptionsHistogram nBins="0" >
      </flowInterruptionsHistogram>
    </Flow>
  </FlowStats>
  <Ipv4FlowClassifier>
    <Flow flowId="1" sourceAddress="10.1.1.1" destinationAddress="10.1.2.1" protocol="6" sourcePort="49153" destinationPort="8080" />
    <Flow flowId="2" sourceAddress="10.1.1.3" destinationAddress="10.1.2.3" protocol="6" sourcePort="49153" destinationPort="8080" />
    <Flow flowId="3" sourceAddress="10.1.1.5" destinationAddress="10.1.2.5" protocol="6" sourcePort="49153" destinationPort="8080" />
    <Flow flowId="4" sourceAddress="10.1.1.7" destinationAddress="10.1.2.7" protocol="6" sourcePort="49153" destinationPort="8080" />
    <Flow flowId="5" sourceAddress="10.1.1.9" destinationAddress="10.1.2.9" protocol="6" sourcePort="49153" destinationPort="8080" />
    <Flow flowId="6" sourceAddress="10.1.1.11" destinationAddress="10.1.2.11" protocol="6" sourcePort="49153" destinationPort="8080" />
    <Flow flowId="7" sourceAddress="10.1.2.1" destinationAddress="10.1.1.1" protocol="6" sourcePort="8080" destinationPort="49153" />
    <Flow flowId="8" sourceAddress="10.1.2.3" destinationAddress="10.1.1.3" protocol="6" sourcePort="8080" destinationPort="49153" />
    <Flow flowId="10" sourceAddress="10.1.2.5" destinationAddress="10.1.1.5" protocol="6" sourcePort="8080" destinationPort="49153" />
    <Flow flowId="11" sourceAddress="10.1.2.7" destinationAddress="10.1.1.7" protocol="6" sourcePort="8080" destinationPort="49153" />
    <Flow flowId="12" sourceAddress="10.1.2.9" destinationAddress="10.1.1.9" protocol="6" sourcePort="8080" destinationPort="49153" />
    <Flow flowId="9" sourceAddress="10.1.2.11" destinationAddress="10.1.1.11" protocol="6" sourcePort="8080" destinationPort="49153" />
  </Ipv4FlowClassifier>
  <Ipv6FlowClassifier>
  </Ipv6FlowClassifier>
  <FlowProbes>
    <FlowProbe index="0">
      <FlowStats  flowId="2" packets="1302" bytes="692672" delayFromFirstProbeSum="+564563846.0ns" >
      </FlowStats>
      <FlowStats  flowId="3" packets="1302" bytes="692672" delayFromFirstProbeSum="+565144059.0ns" >
      </FlowStats>
      <FlowStats  flowId="4" packets="1302" bytes="692672" delayFromFirstProbeSum="+565204884.0ns" >
        <packetsDropped reasonCode="0" number="0" />
        <packetsDropped reasonCode="1" number="0" />
        <packetsDropped reasonCode="2" number="0" />
        <packetsDropped reasonCode="3" number="4" />
        <bytesDropped reasonCode="0" bytes="0" />
        <bytesDropped reasonCode="1" bytes="0" />
        <bytesDropped reasonCode="2" bytes="0" />
        <bytesDropped reasonCode="3" bytes="2352" />
      </FlowStats>
      <FlowStats  flowId="5" packets="1302" bytes="692672" delayFromFirstProbeSum="+566461935.0ns" >
        <packetsDropped reasonCode="0" number="0" />
        <packetsDropped reasonCode="1" number="0" />
        <packetsDropped reasonCode="2" number="0" />
        <packetsDropped reasonCode="3" number="3" />
        <bytesDropped reasonCode="0" bytes="0" />
        <bytesDropped reasonCode="1" bytes="0" />
        <bytesDropped reasonCode="2" bytes="0" />
        <bytesDropped reasonCode="3" bytes="1764" />
      </FlowStats>
      <FlowStats  flowId="7" packets="1299" bytes="67560" delayFromFirstProbeSum="+974693436.0ns" >
      </FlowStats>
      <FlowStats  flowId="9" packets="1299" bytes="67560" delayFromFirstProbeSum="+974693608.0ns" >
      </FlowStats>
      <FlowStats  flowId="11" packets="1299" bytes="67560" delayFromFirstProbeSum="+973812582.0ns" >
      </FlowStats>
      <FlowStats  flowId="12" packets="1299" bytes="67560" delayFromFirstProbeSum="+973361061.0ns" >
      </FlowStats>
    </FlowProbe>
    <FlowProbe index="1">
    </FlowProbe>
    <FlowProbe index="2">
      <FlowStats  flowId="1" packets="1302" bytes="692672" delayFromFirstProbeSum="+564570038.0ns" >
      </FlowStats>
      <FlowStats  flowId="6" packets="1302" bytes="692672" delayFromFirstProbeSum="+564569866.0ns" >
      </FlowStats>
      <FlowStats  flowId="8" packets="1300" bytes="67612" delayFromFirstProbeSum="+526407069.0ns" >
      </FlowStats>
      <FlowStats  flowId="10" packets="1300" bytes="67612" delayFromFirstProbeSum="+525601651.0ns" >
      </FlowStats>
    </FlowProbe>
    <FlowProbe index="3">
    </FlowProbe>
    <FlowProbe index="4">
      <FlowStats  flowId="1" packets="1302" bytes="692672" delayFromFirstProbeSum="+550993880.0ns" >
      </FlowStats>
      <FlowStats  flowId="2" packets="1302" bytes="692672" delayFromFirstProbeSum="+550740543.0ns" >
      </FlowStats>
      <FlowStats  flowId="3" packets="1302" bytes="692672" delayFromFirstProbeSum="+550887262.0ns" >
      </FlowStats>
      <FlowStats  flowId="4" packets="1302" bytes="692672" delayFromFirstProbeSum="+551628456.0ns" >
      </FlowStats>
      <FlowStats  flowId="5" packets="1302" bytes="692672" delayFromFirstProbeSum="+551771695.0ns" >
      </FlowStats>
      <FlowStats  flowId="6" packets="1302" bytes="692672" delayFromFirstProbeSum="+550993708.0ns" >
      </FlowStats>
      <FlowStats  flowId="7" packets="1299" bytes="67560" delayFromFirstProbeSum="+987739345.0ns" >
      </FlowStats>
      <FlowStats  flowId="8" packets="1300" bytes="67612" delayFromFirstProbeSum="+539462978.0ns" >
      </FlowStats>
      <FlowStats  flowId="9" packets="1299" bytes="67560" delayFromFirstProbeSum="+987739474.0ns" >
      </FlowStats>
      <FlowStats  flowId="10" packets="1300" bytes="67612" delayFromFirstProbeSum="+538657560.0ns" >
      </FlowStats>
      <FlowStats  flowId="11" packets="1299" bytes="67560" delayFromFirstProbeSum="+986858534.0ns" >
      </FlowStats>
      <FlowStats  flowId="12" packets="1299" bytes="67560" delayFromFirstProbeSum="+986406927.0ns" >
      </FlowStats>
    </FlowProbe>
    <FlowProbe index="5">
    </FlowProbe>
    <FlowProbe index="6">
      <FlowStats  flowId="1" packets="1302" bytes="692672" delayFromFirstProbeSum="+578146196.0ns" >
      </FlowStats>
      <FlowStats  flowId="2" packets="1302" bytes="692672" delayFromFirstProbeSum="+578339930.0ns" >
      </FlowStats>
      <FlowStats  flowId="3" packets="1302" bytes="692672" delayFromFirstProbeSum="+578720025.0ns" >
      </FlowStats>
      <FlowStats  flowId="4" packets="1302" bytes="692672" delayFromFirstProbeSum="+579109972.0ns" >
      </FlowStats>
      <FlowStats  flowId="5" packets="1302" bytes="692672" delayFromFirstProbeSum="+580310754.0ns" >
      </FlowStats>
      <FlowStats  flowId="6" packets="1302" bytes="692672" delayFromFirstProbeSum="+578146024.0ns" >
      </FlowStats>
      <FlowStats  flowId="7" packets="1299" bytes="67560" delayFromFirstProbeSum="+961647570.0ns" >
      </FlowStats>
      <FlowStats  flowId="8" packets="1300" bytes="67612" delayFromFirstProbeSum="+513351117.0ns" >
      </FlowStats>
      <FlowStats  flowId="9" packets="1299" bytes="67560" delayFromFirstProbeSum="+961647527.0ns" >
      </FlowStats>
      <FlowStats  flowId="10" packets="1300" bytes="67612" delayFromFirstProbeSum="+512545742.0ns" >
      </FlowStats>
      <FlowStats  flowId="11" packets="1299" bytes="67560" delayFromFirstProbeSum="+960766501.0ns" >
      </FlowStats>
      <FlowStats  flowId="12" packets="1299" bytes="67560" delayFromFirstProbeSum="+960315195.0ns" >
      </FlowStats>
    </FlowProbe>
    <FlowProbe index="7">
    </FlowProbe>
    <FlowProbe index="8">
      <FlowStats  flowId="1" packets="1304" bytes="693848" delayFromFirstProbeSum="+0.0ns" >
      </FlowStats>
      <FlowStats  flowId="7" packets="1299" bytes="67560" delayFromFirstProbeSum="+1000785211.0ns" >
      </FlowStats>
    </FlowProbe>
    <FlowProbe index="9">
    </FlowProbe>
    <FlowProbe index="10">
      <FlowStats  flowId="2" packets="1304" bytes="693848" delayFromFirstProbeSum="+0.0ns" >
      </FlowStats>
      <FlowStats  flowId="8" packets="1300" bytes="67612" delayFromFirstProbeSum="+552518887.0ns" >
      </FlowStats>
    </FlowProbe>
    <FlowProbe index="11">
    </FlowProbe>
    <FlowProbe index="12">
      <FlowStats  flowId="3" packets="1304" bytes="693848" delayFromFirstProbeSum="+0.0ns" >
      </FlowStats>
      <FlowStats  flowId="10" packets="1300" bytes="67612" delayFromFirstProbeSum="+551713469.0ns" >
      </FlowStats>
    </FlowProbe>
    <FlowProbe index="13">
    </FlowProbe>
    <FlowProbe index="14">
      <FlowStats  flowId="4" packets="1304" bytes="693848" delayFromFirstProbeSum="+0.0ns" >
      </FlowStats>
      <FlowStats  flowId="11" packets="1299" bytes="67560" delayFromFirstProbeSum="+999904400.0ns" >
      </FlowStats>
    </FlowProbe>
    <FlowProbe index="15">
    </FlowProbe>
    <FlowProbe index="16">
      <FlowStats  flowId="5" packets="1304" bytes="693848" delayFromFirstProbeSum="+0.0ns" >
      </FlowStats>
      <FlowStats  flowId="12" packets="1299" bytes="67560" delayFromFirstProbeSum="+999452793.0ns" >
      </FlowStats>
    </FlowProbe>
    <FlowProbe index="17">
    </FlowProbe>
    <FlowProbe index="18">
      <FlowStats  flowId="6" packets="1304" bytes="693848" delayFromFirstProbeSum="+0.0ns" >
      </FlowStats>
      <FlowStats  flowId="9" packets="1299" bytes="67560" delayFromFirstProbeSum="+1000785340.0ns" >
      </FlowStats>
    </FlowProbe>
    <FlowProbe index="19">
    </FlowProbe>
    <FlowProbe index="20">
      <FlowStats  flowId="1" packets="1301" bytes="692252" delayFromFirstProbeSum="+590610527.0ns" >
      </FlowStats>
      <FlowStats  flowId="7" packets="1301" bytes="67664" delayFromFirstProbeSum="+0.0ns" >
      </FlowStats>
    </FlowProbe>
    <FlowProbe index="21">
    </FlowProbe>
    <FlowProbe index="22">
      <FlowStats  flowId="2" packets="1301" bytes="692252" delayFromFirstProbeSum="+590804127.0ns" >
      </FlowStats>
      <FlowStats  flowId="8" packets="1301" bytes="67664" delayFromFirstProbeSum="+0.0ns" >
      </FlowStats>
    </FlowProbe>
    <FlowProbe index="23">
    </FlowProbe>
    <FlowProbe index="24">
      <FlowStats  flowId="3" packets="1301" bytes="692252" delayFromFirstProbeSum="+591184164.0ns" >
      </FlowStats>
      <FlowStats  flowId="10" packets="1301" bytes="67664" delayFromFirstProbeSum="+0.0ns" >
      </FlowStats>
    </FlowProbe>
    <FlowProbe index="25">
    </FlowProbe>
    <FlowProbe index="26">
      <FlowStats  flowId="4" packets="1301" bytes="692252" delayFromFirstProbeSum="+591574573.0ns" >
      </FlowStats>
      <FlowStats  flowId="11" packets="1301" bytes="67664" delayFromFirstProbeSum="+0.0ns" >
      </FlowStats>
    </FlowProbe>
    <FlowProbe index="27">
    </FlowProbe>
    <FlowProbe index="28">
      <FlowStats  flowId="5" packets="1301" bytes="692252" delayFromFirstProbeSum="+592775355.0ns" >
      </FlowStats>
      <FlowStats  flowId="12" packets="1301" bytes="67664" delayFromFirstProbeSum="+0.0ns" >
      </FlowStats>
    </FlowProbe>
    <FlowProbe index="29">
    </FlowProbe>
    <FlowProbe index="30">
      <FlowStats  flowId="6" packets="1301" bytes="692252" delayFromFirstProbeSum="+590610355.0ns" >
      </FlowStats>
      <FlowStats  flowId="9" packets="1301" bytes="67664" delayFromFirstProbeSum="+0.0ns" >
      </FlowStats>
    </FlowProbe>
    <FlowProbe index="31">
    </FlowProbe>
  </FlowProbes>
</FlowMonitor>
